OBISdat/__init__.py
OBISdat/core_obis.py
OBISdat/obis.py
OBISdat/utils.py
OBISdat-1.4.dist-info/LICENSE
OBISdat-1.4.dist-info/METADATA
OBISdat-1.4.dist-info/WHEEL
OBISdat-1.4.dist-info/entry_points.txt
OBISdat-1.4.dist-info/top_level.txt
OBISdat-1.4.dist-info/RECORD
